skill_audio_recording/LICENSE.md
skill_audio_recording/MANIFEST.in
skill_audio_recording/README.md
skill_audio_recording/__init__.py
skill_audio_recording/requirements.txt
skill_audio_recording/skill.json
skill_audio_recording/version.py
skill_audio_recording/locale/en-us/intents/captains_log.intent
skill_audio_recording/locale/en-us/intents/start_recording.intent
skill_audio_recording/neon_skill_audio_recording.egg-info/PKG-INFO
skill_audio_recording/neon_skill_audio_recording.egg-info/SOURCES.txt
skill_audio_recording/neon_skill_audio_recording.egg-info/dependency_links.txt
skill_audio_recording/neon_skill_audio_recording.egg-info/entry_points.txt
skill_audio_recording/neon_skill_audio_recording.egg-info/top_level.txt
neon_skill_audio_recording-0.0.1.dist-info/LICENSE.md
neon_skill_audio_recording-0.0.1.dist-info/METADATA
neon_skill_audio_recording-0.0.1.dist-info/WHEEL
neon_skill_audio_recording-0.0.1.dist-info/entry_points.txt
neon_skill_audio_recording-0.0.1.dist-info/top_level.txt
neon_skill_audio_recording-0.0.1.dist-info/RECORD
