Metadata-Version: 2.1
Name: neon-skill-audio-recording
Version: 0.0.1
Summary: Audio recording skill
Home-page: https://github.com/NeonGeckoCom/skill-audio-recording
Author: Neongecko
Author-email: developers@neon.ai
License: BSD-3-Clause
License-File: LICENSE.md
